{
  "appPageId" : "a1055a9c-8c31-4964-a684-80c675b9640c",
  "componentName" : "community_layout:sldsFlexibleLayout",
  "dataProviders" : [ {
    "componentName" : "commerce_data_provider:searchDataProvider",
    "componentAttributes" : {
      "searchTerm" : "{!Route.term}",
      "sfdcExpressionKey" : "Search",
      "categoryPathId" : "{!Route.recordId}",
      "categoryId" : "{!Route.recordId}"
    }
  } ],
  "id" : "034f5855-0cfd-44fe-b348-1ea6deabb5d3",
  "label" : "Category",
  "regions" : [ {
    "components" : [ {
      "componentAttributes" : {
        "backgroundImageConfig" : "",
        "backgroundImageOverlay" : "rgba(0,0,0,0)",
        "sectionConfig" : "{\"UUID\":\"a55d4372-465f-4ca4-99cf-9ae92fc18773\",\"columns\":[{\"UUID\":\"ef08dcd9-1f4d-4f38-9bb1-2e54e0e4de39\",\"columnName\":\"Column 1\",\"columnKey\":\"col1\",\"columnWidth\":\"12\",\"seedComponents\":null}]}"
      },
      "componentName" : "community_layout:section",
      "id" : "a55d4372-465f-4ca4-99cf-9ae92fc18773",
      "regions" : [ {
        "components" : [ {
          "componentAttributes" : {
            "divider" : "chevron",
            "hideOnMobile" : false,
            "maxDepthOnMobile" : "3",
            "showHomeLink" : true,
            "showLastItemAsLink" : false,
            "textSize" : "small"
          },
          "componentName" : "commerce_builder:breadcrumbs",
          "id" : "6863eecb-8172-45a6-a382-4237565795ef",
          "renderPriority" : "NEUTRAL",
          "renditionMap" : { },
          "type" : "component"
        } ],
        "id" : "ef08dcd9-1f4d-4f38-9bb1-2e54e0e4de39",
        "regionLabel" : "Column 1",
        "regionName" : "col1",
        "renditionMap" : { },
        "type" : "region"
      } ],
      "renderPriority" : "NEUTRAL",
      "renditionMap" : { },
      "scopedBrandingSetId" : null,
      "type" : "component"
    }, {
      "componentAttributes" : {
        "backgroundImageConfig" : "",
        "backgroundImageOverlay" : "rgba(0,0,0,0)",
        "sectionConfig" : "{\"UUID\":\"db590892-d8ce-4cf3-9a62-641d07addd59\",\"columns\":[{\"UUID\":\"f3d01035-ba7b-43c6-89bc-a2ab87be70d4\",\"columnName\":\"Column 1\",\"columnKey\":\"col1\",\"columnWidth\":\"12\",\"seedComponents\":null}]}"
      },
      "componentName" : "community_layout:section",
      "id" : "db590892-d8ce-4cf3-9a62-641d07addd59",
      "regions" : [ {
        "components" : [ {
          "componentAttributes" : {
            "categoryId" : "{!Route.recordId}",
            "titleColor" : "rgb(0, 0, 0)"
          },
          "componentName" : "b2c_lite_commerce:categoryBanner",
          "id" : "24e178f6-31a1-4bea-ab0f-9d84d240c3cc",
          "renderPriority" : "NEUTRAL",
          "renditionMap" : { },
          "type" : "component"
        }, {
          "componentAttributes" : { },
          "componentName" : "commerce_builder:searchResultsLayout",
          "id" : "d2641b31-e239-4da4-b54b-18d44e98ebca",
          "regions" : [ {
            "components" : [ {
              "componentAttributes" : {
                "backgroundColor" : "",
                "paddingHorizontal" : "none",
                "paddingVertical" : "none",
                "text" : "{!Search.Results.categoryName}",
                "textAlign" : "left",
                "textDecoration" : "{}",
                "textDisplayInfo" : "{\"headingTag\": \"h1\", \"textStyle\": \"heading-xlarge\"}"
              },
              "componentName" : "dxp_base:textBlock",
              "id" : "0faf947d-04db-4a69-8157-7edb59addfec",
              "renderPriority" : "NEUTRAL",
              "renditionMap" : { },
              "type" : "component"
            } ],
            "id" : "a7046ac3-2978-4925-9725-29e0c8a00851",
            "regionName" : "categoryHeader",
            "type" : "region"
          }, {
            "components" : [ {
              "componentAttributes" : {
                "backgroundColor" : "",
                "paddingHorizontal" : "small",
                "paddingVertical" : "small",
                "text" : "{!Search.Results.description}",
                "textAlign" : "left",
                "textDecoration" : "{}",
                "textDisplayInfo" : "{\"headingTag\": \"h3\", \"textStyle\": \"heading-medium\"}"
              },
              "componentName" : "dxp_base:textBlock",
              "id" : "81b2ad1e-fd95-4fd2-a1b9-a98fd9771646",
              "renderPriority" : "NEUTRAL",
              "renditionMap" : { },
              "type" : "component"
            } ],
            "id" : "9b8de03c-1ac8-480d-8ae2-fe903d12ac44",
            "regionName" : "searchHeader",
            "type" : "region"
          }, {
            "components" : [ {
              "componentAttributes" : {
                "sortRuleId" : "{!Search.SortRules.currentSortRuleId}",
                "sortRules" : "{!Search.SortRules.rules}"
              },
              "componentName" : "commerce_builder:searchSortMenu",
              "id" : "cdb68e7c-9e7c-4459-82a5-a49c95de2cfe",
              "regions" : [ {
                "components" : [ {
                  "componentAttributes" : {
                    "backgroundColor" : "",
                    "paddingHorizontal" : "small",
                    "paddingVertical" : "none",
                    "text" : "{!Label.B2B_Search_Results.sortBy}",
                    "textAlign" : "right",
                    "textDecoration" : "{}",
                    "textDisplayInfo" : "{ \"headingTag\": \"p\", \"textStyle\": \"body-regular\" }"
                  },
                  "componentName" : "dxp_base:textBlock",
                  "id" : "6f6d46aa-8a3a-44e5-a737-48a90b0c0bdb",
                  "renderPriority" : "NEUTRAL",
                  "renditionMap" : { },
                  "type" : "component"
                } ],
                "id" : "5bf701ce-b238-4a54-b87a-25e1ce9d3e3f",
                "regionName" : "sortMenuLabel",
                "type" : "region"
              } ],
              "renderPriority" : "NEUTRAL",
              "renditionMap" : { },
              "type" : "component"
            } ],
            "id" : "b67580f2-cb7e-442b-b133-389e6ce3f5b6",
            "regionName" : "sortingMenu",
            "type" : "region"
          }, {
            "components" : [ {
              "componentAttributes" : {
                "searchResults" : "{!Search.Results}"
              },
              "componentName" : "commerce_builder:searchFilters",
              "id" : "08c1b562-6899-4248-afd2-ca4a8f6fa703",
              "renderPriority" : "NEUTRAL",
              "renditionMap" : { },
              "type" : "component"
            } ],
            "id" : "8433a035-ecab-4fa9-9dfd-753c1a6e6003",
            "regionName" : "searchFilters",
            "type" : "region"
          }, {
            "components" : [ {
              "componentAttributes" : {
                "addToCartButtonProcessingText" : "Adding...",
                "addToCartButtonStyle" : "primary",
                "addToCartButtonText" : "Add to cart",
                "cardAlignment" : "center",
                "cardBorderRadius" : "1",
                "cardContentMapping" : "[{\"name\":\"Name\",\"showLabel\":false,\"label\":\"Product Name\",\"fontSize\":\"medium\"},{\"name\":\"StockKeepingUnit\",\"showLabel\":true,\"label\":\"SKU\",\"type\":\"STRING\",\"fontSize\":\"small\",\"fontColor\":\"#1c1c1c\"}]",
                "gridColumnSpacing" : "small",
                "gridMaxColumnsDisplayed" : "3",
                "gridRowSpacing" : "small",
                "incrementValueGuideText" : "Increment quantity is {0}",
                "listRowSpacing" : "small",
                "maximumValueGuideText" : "Maximum quantity is {0}",
                "minimumValueGuideText" : "Minimum quantity is {0}",
                "negotiatedPriceTextSize" : "medium",
                "originalPriceTextSize" : "medium",
                "quantitySelectorLabel" : "QTY",
                "resultsLayout" : "list",
                "searchResults" : "{!Search.Results}",
                "searchResultsFields" : "{!Search.Name},{!Search.StockKeepingUnit}",
                "showCallToActionButton" : true,
                "showNegotiatedPrice" : true,
                "showOriginalPrice" : true,
                "showProductImage" : true,
                "viewOptionsButtonText" : "View options"
              },
              "componentName" : "commerce_builder:searchResults",
              "id" : "7baaaa48-2bb8-4c4b-9a21-88e4b7f7b19e",
              "renderPriority" : "NEUTRAL",
              "renditionMap" : { },
              "type" : "component"
            } ],
            "id" : "de6a6bb3-2613-48f0-913f-e8862acdafc8",
            "regionName" : "searchResult",
            "type" : "region"
          } ],
          "renderPriority" : "NEUTRAL",
          "renditionMap" : { },
          "type" : "component"
        } ],
        "id" : "f3d01035-ba7b-43c6-89bc-a2ab87be70d4",
        "regionLabel" : "Column 1",
        "regionName" : "col1",
        "renditionMap" : { },
        "type" : "region"
      } ],
      "renderPriority" : "NEUTRAL",
      "renditionMap" : { },
      "scopedBrandingSetId" : null,
      "type" : "component"
    } ],
    "id" : "78cb62a9-99d2-43e0-a948-3cba129e43d8",
    "regionName" : "content",
    "type" : "region"
  }, {
    "components" : [ {
      "componentAttributes" : {
        "customHeadTags" : "",
        "description" : "",
        "pageTitle" : "{!Record._Object}: {!Record._Title}",
        "recordId" : "{!recordId}"
      },
      "componentName" : "community_builder:seoAssistant",
      "id" : "aeceb358-ad42-407a-a714-d9328d5c836b",
      "renderPriority" : "NEUTRAL",
      "renditionMap" : { },
      "type" : "component"
    } ],
    "id" : "bffecd80-de20-4138-8ee8-3917016ef500",
    "regionName" : "sfdcHiddenRegion",
    "type" : "region"
  } ],
  "themeLayoutType" : "Inner",
  "type" : "view",
  "viewType" : "detail-0ZG"
}