{
  "appPageId" : "bbb080ed-a03c-40b0-ad33-67bbfdca959b",
  "componentName" : "community_layout:sldsFlexibleLayout",
  "dataProviders" : [ ],
  "id" : "56e2d541-2305-4ecc-9aad-0a631516a0da",
  "label" : "Too Many Requests",
  "regions" : [ {
    "components" : [ {
      "componentAttributes" : {
        "backgroundImageConfig" : "",
        "backgroundImageOverlay" : "rgba(0,0,0,0)",
        "sectionConfig" : "{\"UUID\":\"4c616d1c-691e-4402-bb05-ac6dd66f24a4\",\"columns\":[{\"UUID\":\"ecb24032-a9de-4d2e-88e7-e4dc597d07a7\",\"columnName\":\"Column 1\",\"columnKey\":\"col1\",\"columnWidth\":\"12\",\"seedComponents\":null}]}"
      },
      "componentName" : "community_layout:section",
      "id" : "4c616d1c-691e-4402-bb05-ac6dd66f24a4",
      "regions" : [ {
        "components" : [ {
          "componentAttributes" : {
            "richTextValue" : "<div style=\"display: flex; align-items: center; flex-direction: column; margin: 60px 25px 30px 25px;\">\n\t<div style=\"background-image: url(assets/images/tooManyRequests.svg); background-size: contain; height: 350px; width: 100%; background-repeat: no-repeat; background-position: center;\"></div>\n</div>\n<div style=\"margin: 0 25px; text-align: center;\">\n\t<h1 class=\"slds-text-heading_large\">Looks like the site is experiencing higher than usual demand&#8230;</h1>\n\t<p class=\"slds-text-heading_small\">Don't go anywhere. We'll redirect you in a moment.</p>\n</div>"
          },
          "componentName" : "community_builder:htmlEditor",
          "id" : "05a8727a-cd81-4b8f-9f77-a3c1b29aaefa",
          "renderPriority" : "NEUTRAL",
          "renditionMap" : { },
          "type" : "component"
        }, {
          "componentAttributes" : { },
          "componentName" : "experience_availability:autoRefresh",
          "id" : "b90d073f-89cf-4c49-bb9c-cccd1aeeaad7",
          "renderPriority" : "NEUTRAL",
          "renditionMap" : { },
          "type" : "component"
        } ],
        "id" : "ecb24032-a9de-4d2e-88e7-e4dc597d07a7",
        "regionLabel" : "Column 1",
        "regionName" : "col1",
        "renditionMap" : { },
        "type" : "region"
      } ],
      "renderPriority" : "NEUTRAL",
      "renditionMap" : { },
      "scopedBrandingSetId" : null,
      "type" : "component"
    } ],
    "id" : "9d0d4d34-c473-4b60-8c8f-cee047a96a39",
    "regionName" : "content",
    "type" : "region"
  } ],
  "themeLayoutType" : "ServiceNotAvailable",
  "type" : "view",
  "viewType" : "too-many-requests"
}